jprint2/__init__.py
jprint2/jprint.py
jprint2-0.4.0.dist-info/METADATA
jprint2-0.4.0.dist-info/WHEEL
jprint2-0.4.0.dist-info/licenses/LICENSE
jprint2-0.4.0.dist-info/RECORD
